<annotation>
  <folder>HQ_analog</folder>
  <filename>09c2e201a7c997f61ecfed747772f8adc4c3f25a</filename>
  <path>/Users/wangning/Desktop/+: NBFD/HQ_analog/09c2e201a7c997f61ecfed747772f8adc4c3f25a.jpg</path>
  <source>
    <database>Unknown</database>
  </source>
  <size>
    <width>2048</width>
    <height>1152</height>
    <depth>3</depth>
  </size>
  <segmented>0</segmented>
  <object>
    <name>0</name>
    <pose>Unspecified</pose>
    <truncated>0</truncated>
    <difficult>0</difficult>
    <bndbox>
      <xmin>263</xmin>
      <ymin>563</ymin>
      <xmax>465</xmax>
      <ymax>840</ymax>
    </bndbox>
  </object>
  <object>
    <name>7</name>
    <pose>Unspecified</pose>
    <truncated>0</truncated>
    <difficult>0</difficult>
    <bndbox>
      <xmin>686</xmin>
      <ymin>523</ymin>
      <xmax>878</xmax>
      <ymax>836</ymax>
    </bndbox>
  </object>
  <object>
    <name>1</name>
    <pose>Unspecified</pose>
    <truncated>0</truncated>
    <difficult>0</difficult>
    <bndbox>
      <xmin>1076</xmin>
      <ymin>540</ymin>
      <xmax>1259</xmax>
      <ymax>807</ymax>
    </bndbox>
  </object>
  <object>
    <name>5</name>
    <pose>Unspecified</pose>
    <truncated>0</truncated>
    <difficult>0</difficult>
    <bndbox>
      <xmin>1470</xmin>
      <ymin>544</ymin>
      <xmax>1651</xmax>
      <ymax>805</ymax>
    </bndbox>
  </object>
</annotation>
