<annotation>
  <folder>HQ_analog</folder>
  <filename>0df530261af7f709ba91a8c9538183124288cea9</filename>
  <path>Datasets/img/0df530261af7f709ba91a8c9538183124288cea9.jpg</path>
  <source>
    <database>Unknown</database>
  </source>
  <size>
    <width>2048</width>
    <height>1152</height>
    <depth>3</depth>
  </size>
  <segmented>0</segmented>
  <object>
    <name>0</name>
    <pose>Unspecified</pose>
    <truncated>0</truncated>
    <difficult>0</difficult>
    <bndbox>
      <xmin>68</xmin>
      <ymin>582</ymin>
      <xmax>290</xmax>
      <ymax>830</ymax>
    </bndbox>
  </object>
  <object>
    <name>0</name>
    <pose>Unspecified</pose>
    <truncated>0</truncated>
    <difficult>0</difficult>
    <bndbox>
      <xmin>435</xmin>
      <ymin>595</ymin>
      <xmax>644</xmax>
      <ymax>824</ymax>
    </bndbox>
  </object>
  <object>
    <name>2</name>
    <pose>Unspecified</pose>
    <truncated>0</truncated>
    <difficult>0</difficult>
    <bndbox>
      <xmin>816</xmin>
      <ymin>598</ymin>
      <xmax>1015</xmax>
      <ymax>839</ymax>
    </bndbox>
  </object>
  <object>
    <name>8</name>
    <pose>Unspecified</pose>
    <truncated>0</truncated>
    <difficult>0</difficult>
    <bndbox>
      <xmin>1192</xmin>
      <ymin>604</ymin>
      <xmax>1370</xmax>
      <ymax>820</ymax>
    </bndbox>
  </object>
  <object>
    <name>0</name>
    <pose>Unspecified</pose>
    <truncated>0</truncated>
    <difficult>0</difficult>
    <bndbox>
      <xmin>1565</xmin>
      <ymin>583</ymin>
      <xmax>1727</xmax>
      <ymax>828</ymax>
    </bndbox>
  </object>
</annotation>